logfy/__init__.py
logfy/decrypt.py
logfy/log.py
logfy/secure.py
logfy-1.0.0.dist-info/METADATA
logfy-1.0.0.dist-info/WHEEL
logfy-1.0.0.dist-info/top_level.txt
logfy-1.0.0.dist-info/RECORD
