Metadata-Version: 2.1
Name: logfy
Version: 1.0.0
Summary: Beautiful logs and encrypted, tamper-proof files
Author: lynariksh
License: Apache License 2.0
Requires-Dist: logcrypt>=1.0.0
Requires-Dist: colorlog>=3.0.0
